addongen/__componentbinding__.py
addongen/__entitybinding__.py
addongen/__entityquery__.py
addongen/__eventbinding__.py
addongen/__init__.py
addongen/__object__.py
addongen/__slashcommand__.py
addongen/__systemevent__.py
addongen/client.py
addongen/clientevent.py
addongen/server.py
addongen/serverevent.py
addongen-0.0.2.dist-info/LICENSE
addongen-0.0.2.dist-info/METADATA
addongen-0.0.2.dist-info/WHEEL
addongen-0.0.2.dist-info/top_level.txt
addongen-0.0.2.dist-info/RECORD
